pnzer/__init__.py
pnzer/__version__.py
pnzer-0.0.2.dist-info/LICENSE
pnzer-0.0.2.dist-info/METADATA
pnzer-0.0.2.dist-info/WHEEL
pnzer-0.0.2.dist-info/top_level.txt
pnzer-0.0.2.dist-info/RECORD
