Metadata-Version: 2.1
Name: pnzer
Version: 0.0.2
Summary: UNKNOWN
Home-page: https://github.com/ianolpx/pnzer
Author: Hans Park
Author-email: ianolpx@gmail.com
License: MIT
Platform: UNKNOWN
Classifier: Programming Language :: Python :: 3.6
Classifier: Programming Language :: Python :: 3.7
Classifier: Programming Language :: Python :: 3.8
Classifier: Programming Language :: Python :: 3.9
Classifier: Programming Language :: Python :: 3.10
Classifier: License :: OSI Approved :: MIT License
Classifier: Operating System :: OS Independent
Requires-Python: >=3.5
License-File: LICENSE
Requires-Dist: pandas
Requires-Dist: scikit-learn
